drawille.py
drawille-0.2.0.dist-info/LICENSE
drawille-0.2.0.dist-info/METADATA
drawille-0.2.0.dist-info/WHEEL
drawille-0.2.0.dist-info/top_level.txt
drawille-0.2.0.dist-info/RECORD
