Metadata-Version: 2.1
Name: drawille
Version: 0.2.0
Summary: Drawing in terminal with unicode braille characters
Home-page: https://github.com/asciimoo/drawille
Download-URL: https://github.com/asciimoo/drawille/tarball/master
Author: Adam Tauber
Author-email: asciimoo@gmail.com
License: AGPLv3+
Keywords: terminal braille drawing canvas console
Classifier: Development Status :: 4 - Beta
Classifier: Topic :: Utilities
Classifier: Environment :: Console
Classifier: License :: OSI Approved :: GNU Affero General Public License v3
Classifier: Intended Audience :: Developers
Classifier: Natural Language :: English
Classifier: Programming Language :: Python
Classifier: Programming Language :: Python :: 2.6
Classifier: Programming Language :: Python :: 2.7
Classifier: Programming Language :: Python :: 3
Classifier: Programming Language :: Python :: 3.3
License-File: LICENSE
